odoo10_addon_mail_as_letter-10.0.1.0.1-py3.8-nspkg.pth
odoo/addons/mail_as_letter/README.rst
odoo/addons/mail_as_letter/__init__.py
odoo/addons/mail_as_letter/__manifest__.py
odoo/addons/mail_as_letter/i18n/ca.po
odoo/addons/mail_as_letter/i18n/de.po
odoo/addons/mail_as_letter/i18n/es.po
odoo/addons/mail_as_letter/i18n/es_CO.po
odoo/addons/mail_as_letter/i18n/fr.po
odoo/addons/mail_as_letter/i18n/hr.po
odoo/addons/mail_as_letter/i18n/it.po
odoo/addons/mail_as_letter/i18n/mail_as_letter.pot
odoo/addons/mail_as_letter/i18n/nl_NL.po
odoo/addons/mail_as_letter/i18n/pt_BR.po
odoo/addons/mail_as_letter/i18n/sl.po
odoo/addons/mail_as_letter/i18n/zh_CN.po
odoo/addons/mail_as_letter/report/mail_as_letter_qweb.xml
odoo/addons/mail_as_letter/static/description/icon.png
odoo/addons/mail_as_letter/tests/__init__.py
odoo/addons/mail_as_letter/tests/test_mail_as_letter.py
odoo/addons/mail_as_letter/wizards/__init__.py
odoo/addons/mail_as_letter/wizards/mail_compose_message.py
odoo/addons/mail_as_letter/wizards/mail_compose_message.xml
odoo10_addon_mail_as_letter-10.0.1.0.1.dist-info/METADATA
odoo10_addon_mail_as_letter-10.0.1.0.1.dist-info/WHEEL
odoo10_addon_mail_as_letter-10.0.1.0.1.dist-info/namespace_packages.txt
odoo10_addon_mail_as_letter-10.0.1.0.1.dist-info/top_level.txt
odoo10_addon_mail_as_letter-10.0.1.0.1.dist-info/RECORD
